bitloom/core.py
bitloom/init.py
bitloom-0.1.0.dist-info/METADATA
bitloom-0.1.0.dist-info/WHEEL
bitloom-0.1.0.dist-info/top_level.txt
bitloom-0.1.0.dist-info/RECORD
