Metadata-Version: 2.4
Name: bitloom
Version: 0.1.0
Summary: Minimal Bitloom lang processor
Author: mav
License: MIT
